ofxstatement_hype-1.0.1-py3.11-nspkg.pth
ofxstatement/plugins/hype.py
ofxstatement/plugins/hypeMovementsPdfParser.py
ofxstatement/plugins/hypeTransaction.py
ofxstatement_hype-1.0.1.dist-info/METADATA
ofxstatement_hype-1.0.1.dist-info/WHEEL
ofxstatement_hype-1.0.1.dist-info/entry_points.txt
ofxstatement_hype-1.0.1.dist-info/namespace_packages.txt
ofxstatement_hype-1.0.1.dist-info/top_level.txt
ofxstatement_hype-1.0.1.dist-info/zip-safe
ofxstatement_hype-1.0.1.dist-info/RECORD
