Metadata-Version: 2.1
Name: ofxstatement-hype
Version: 1.0.1
Summary: Hype plugin for ofxstatement
Home-page: https://github.com/lorenzogiudici5/ofxstatement-hype
Author: Lorenzo Giudici
Author-email: lorenzogiudici5@proton.com
License: GPLv3
Keywords: ofx,banking,statement,hype
Classifier: Development Status :: 5 - Production/Stable
Classifier: Programming Language :: Python :: 3
Classifier: Natural Language :: English
Classifier: Topic :: Office/Business :: Financial :: Accounting
Classifier: Topic :: Utilities
Classifier: Environment :: Console
Classifier: Operating System :: OS Independent
Classifier: License :: OSI Approved :: GNU General Public License v3 (GPLv3)
Requires-Dist: ofxstatement
Requires-Dist: pandas
Requires-Dist: tabula-py
Requires-Dist: pypdf2
Provides-Extra: test
Requires-Dist: pytest ; extra == 'test'
